logiclayer_merge/__init__.py
logiclayer_merge/exceptions.py
logiclayer_merge/models.py
logiclayer_merge/module.py
logiclayer_merge-0.1.1.dist-info/METADATA
logiclayer_merge-0.1.1.dist-info/WHEEL
logiclayer_merge-0.1.1.dist-info/RECORD
