Metadata-Version: 2.4
Name: logiclayer-merge
Version: 0.1.1
Summary: Allows to merge the results of other LogicLayer modules in a single response.
Project-URL: repository, https://github.com/Datawheel/logiclayer-merge
Requires-Python: <3.14,>=3.9
Requires-Dist: httpx<0.29.0,>=0.28.1
Requires-Dist: logiclayer>=0.4.1
Requires-Dist: polars>=1.23.0
Requires-Dist: pydantic>=2.10.6
Requires-Dist: tesseract-olap[clickhouse]<0.23.0,>=0.22.6
